[{"id": 4395217, "categoryName": "skruemaskiner", "imageUrl": "https://www.pricerunner.dk/product/640x640/1745964048/Makita-DHR171Z-Solo.jpg", "name": "Makita DHR171Z Solo", "merchantName": "Prishammeren", "offerUrl": "https://pricerunner.com/gotostore/v1/partner/DK/ce84581861eddeabd1428c1c49748679/adrunner_dk_mandeportalen?productId=4395217", "price": "1049.00", "shippingCost": "45.00", "stockStatus": "P\u00e5 lager", "raekkefoelge": 9}, {"id": 5112088, "categoryName": "jakker herre", "imageUrl": "https://www.pricerunner.dk/product/640x640/3000074837/Patagonia-Men-s-Retro-Pile-Fleece-Jacket-El-Cap-Khaki.jpg", "name": "Patagonia Men's Retro Pile Fleece Jacket - El Cap Khaki", "merchantName": "Lystfisk.dk", "offerUrl": "https://pricerunner.com/gotostore/v1/partner/DK/5c6f0696f4ecdc108a3a67587cdccd9f/adrunner_dk_mandeportalen?productId=5112088", "price": "1099.00", "shippingCost": "0.00", "stockStatus": "P\u00e5 lager", "raekkefoelge": 3}, {"id": 4361884, "categoryName": "skruemaskiner", "imageUrl": "https://www.pricerunner.dk/product/640x640/3014994343/Dewalt-DCD777S2T-QW-%282x1.5Ah%29.jpg", "name": "Dewalt DCD777S2T-QW (2x1.5Ah)", "merchantName": "10-4", "offerUrl": "https://pricerunner.com/gotostore/v1/partner/DK/f6d80d66c956425e2e4f960927e1bb9a/adrunner_dk_mandeportalen?productId=4361884", "price": "1099.00", "shippingCost": "45.00", "stockStatus": "P\u00e5 lager", "raekkefoelge": 2}, {"id": 5043143, "categoryName": "projektorer", "imageUrl": "https://www.pricerunner.dk/product/640x640/3000534137/Epson-EH-TW7100.jpg", "name": "Epson EH-TW7100", "merchantName": "HIFI Klubben", "offerUrl": "https://pricerunner.com/gotostore/v1/partner/DK/5634ed30c8f40df628954122bb1af0d5/adrunner_dk_mandeportalen?productId=5043143", "price": "11345.00", "shippingCost": "0.00", "stockStatus": "P\u00e5 lager", "raekkefoelge": 2}, {"id": 4982323, "categoryName": "pladespiller", "imageUrl": "https://www.pricerunner.dk/product/640x640/3006920817/Audio-Technica-AT-LP60XUSB.jpg", "name": "Audio-Technica AT-LP60XUSB", "merchantName": "happii.dk", "offerUrl": "https://pricerunner.com/gotostore/v1/partner/DK/3f68def7c96a81eed780b7116849f7fc/adrunner_dk_mandeportalen?productId=4982323", "price": "1170.00", "shippingCost": "33.00", "stockStatus": "P\u00e5 lager", "raekkefoelge": 4}, {"id": 3200253885, "categoryName": "projektorer", "imageUrl": "https://www.pricerunner.dk/product/640x640/3002348778/Xgimi-Horizon-Pro.jpg", "name": "Xgimi Horizon Pro", "merchantName": "Elgiganten", "offerUrl": "https://pricerunner.com/gotostore/v1/partner/DK/d76c3743a2c5ea1f5b8e8493ab9a4595/adrunner_dk_mandeportalen?productId=3200253885", "price": "11769.00", "shippingCost": "39.00", "stockStatus": "P\u00e5 lager", "raekkefoelge": 9}, {"id": 2663748, "categoryName": "barbermaskiner", "imageUrl": "https://www.pricerunner.dk/product/640x640/3006625220/Panasonic-ER-GN30.jpg", "name": "Panasonic ER-GN30", "merchantName": "happii.dk", "offerUrl": "https://pricerunner.com/gotostore/v1/partner/DK/8c4508abdfdb99dc64aaa6a72675264e/adrunner_dk_mandeportalen?productId=2663748", "price": "124.00", "shippingCost": "33.00", "stockStatus": "P\u00e5 lager", "raekkefoelge": 4}, {"id": 3200125765, "categoryName": "pladespiller", "imageUrl": "https://www.pricerunner.dk/product/640x640/3001375964/Teac-TN-180BT-A3.jpg", "name": "Teac TN-180BT-A3", "merchantName": "happii.dk", "offerUrl": "https://pricerunner.com/gotostore/v1/partner/DK/7bc4cf79d6277e0d792f798b7ba5d7d4/adrunner_dk_mandeportalen?productId=3200125765", "price": "1255.00", "shippingCost": "33.00", "stockStatus": "P\u00e5 lager", "raekkefoelge": 7}, {"id": 3500190, "categoryName": "skruemaskiner", "imageUrl": "https://www.pricerunner.dk/product/640x640/1610295097/Makita-DTD154Z-Solo.jpg", "name": "Makita DTD154Z Solo", "merchantName": "10-4", "offerUrl": "https://pricerunner.com/gotostore/v1/partner/DK/e017ec26945fb8fa35d62495eff565ef/adrunner_dk_mandeportalen?productId=3500190", "price": "1289.00", "shippingCost": "0.00", "stockStatus": "P\u00e5 lager", "raekkefoelge": 8}, {"id": 3202470215, "categoryName": "tr\u00e5dl\u00f8se h\u00f8retelefoner", "imageUrl": "https://www.pricerunner.dk/product/640x640/3006245866/Apple-AirPods-%283rd-generation%29-with-Lightning-Charging-Case.jpg", "name": "Apple AirPods (3rd generation) with Lightning Charging Case", "merchantName": "Amazon DE", "offerUrl": "https://pricerunner.com/gotostore/v1/partner/DK/38e1ed2dd4d0531bef35dd776246db2b/adrunner_dk_mandeportalen?productId=3202470215", "price": "1334.96", "shippingCost": "55.93", "stockStatus": "P\u00e5 lager", "raekkefoelge": 4}, {"id": 3200466715, "categoryName": "tr\u00e5dl\u00f8se h\u00f8retelefoner", "imageUrl": "https://www.pricerunner.dk/product/640x640/3003053640/Apple-AirPods-%283rd-generation%29-with-MagSafe-Charging-Case.jpg", "name": "Apple AirPods (3rd generation) with MagSafe Charging Case", "merchantName": "Bilka.dk", "offerUrl": "https://pricerunner.com/gotostore/v1/partner/DK/bb1c18e4b14bce6777b61faab7ce8e1a/adrunner_dk_mandeportalen?productId=3200466715", "price": "1399.00", "shippingCost": "34.00", "stockStatus": "P\u00e5 lager", "raekkefoelge": 7}, {"id": 3202798430, "categoryName": "skruemaskiner", "imageUrl": "https://www.pricerunner.dk/product/640x640/3006718158/Makita-DTD172Z-Solo.jpg", "name": "Makita DTD172Z Solo", "merchantName": "Prishammeren", "offerUrl": "https://pricerunner.com/gotostore/v1/partner/DK/c12f2529ffcedac49f0e664d6466cf27/adrunner_dk_mandeportalen?productId=3202798430", "price": "1559.00", "shippingCost": "45.00", "stockStatus": "P\u00e5 lager", "raekkefoelge": 6}, {"id": 3203663312, "categoryName": "jakker herre", "imageUrl": "https://www.pricerunner.dk/product/640x640/3007665333/Peak-Performance-Down-Liner-Hood-Jacket.jpg", "name": "Peak Performance Down Liner Hood Jacket", "merchantName": "Billigsport", "offerUrl": "https://pricerunner.com/gotostore/v1/partner/DK/3eb682ff5c562a8c35c09a657b717ad4/adrunner_dk_mandeportalen?productId=3203663312", "price": "1574.96", "shippingCost": "0.00", "stockStatus": "P\u00e5 lager", "raekkefoelge": 4}, {"id": 3203737630, "categoryName": "pladespiller", "imageUrl": "https://www.pricerunner.dk/product/640x640/3007743969/AT-LP60XBT.jpg", "name": "AT-LP60XBT", "merchantName": "Dustin Home", "offerUrl": "https://pricerunner.com/gotostore/v1/partner/DK/746e4bbac094123aef24b1ecf9b484f6/adrunner_dk_mandeportalen?productId=3203737630", "price": "1590.00", "shippingCost": "69.00", "stockStatus": "P\u00e5 lager", "raekkefoelge": 2}, {"id": 4982268, "categoryName": "pladespiller", "imageUrl": "https://www.pricerunner.dk/product/640x640/1889898563/Pro-Ject-Primary-E.jpg", "name": "Pro-Ject Primary E", "merchantName": "AV-Connection", "offerUrl": "https://pricerunner.com/gotostore/v1/partner/DK/5c21d806866f2756fe4c9c3d149d3437/adrunner_dk_mandeportalen?productId=4982268", "price": "1595.00", "shippingCost": "0.00", "stockStatus": "P\u00e5 lager", "raekkefoelge": 9}, {"id": 3203618213, "categoryName": "pladespiller", "imageUrl": "https://www.pricerunner.dk/product/640x640/3012106460/Sony-PS-LX310BT.jpg", "name": "Sony PS-LX310BT", "merchantName": "Komplett.dk", "offerUrl": "https://pricerunner.com/gotostore/v1/partner/DK/b72497f0ecc15cae7ed6b2f10e33f2b2/adrunner_dk_mandeportalen?productId=3203618213", "price": "1699.00", "shippingCost": "0.00", "stockStatus": "P\u00e5 lager", "raekkefoelge": 1}, {"id": 5081358, "categoryName": "elektronisk p-skive", "imageUrl": "https://www.pricerunner.dk/product/640x640/3045181148/Park-Deluxe-Digital-FS42.jpg", "name": "Park Deluxe Digital FS42", "merchantName": "jem & fix", "offerUrl": "https://pricerunner.com/gotostore/v1/partner/DK/ed907b6de5a0b3487292c3b94964224a/adrunner_dk_mandeportalen?productId=5081358", "price": "171.00", "shippingCost": "38.00", "stockStatus": "P\u00e5 lager", "raekkefoelge": 9}, {"id": 3207768130, "categoryName": "smartwatch", "imageUrl": "https://www.pricerunner.dk/product/640x640/3012361948/Samsung-Galaxy-Watch6-40mm-BT.jpg", "name": "Samsung Galaxy Watch6 40mm BT", "merchantName": "NordicElectronics", "offerUrl": "https://pricerunner.com/gotostore/v1/partner/DK/7502c4e91f43d2e7dcbd6986f177dca6/adrunner_dk_mandeportalen?productId=3207768130", "price": "1722.00", "shippingCost": "49.00", "stockStatus": "P\u00e5 lager", "raekkefoelge": 8}, {"id": 3207649934, "categoryName": "barbermaskiner", "imageUrl": "https://www.pricerunner.dk/product/640x640/3012185331/Philips-OneBlade-QP2724.jpg", "name": "Philips OneBlade QP2724", "merchantName": "Bilka.dk", "offerUrl": "https://pricerunner.com/gotostore/v1/partner/DK/72e9ac2f5fae7583003eb1fc4e804689/adrunner_dk_mandeportalen?productId=3207649934", "price": "175.00", "shippingCost": "34.00", "stockStatus": "P\u00e5 lager", "raekkefoelge": 6}, {"id": 3271581, "categoryName": "parfumer herre", "imageUrl": "https://www.pricerunner.dk/product/640x640/1585672117/Nikos-Sculpture-Homme-EdT-100ml.jpg", "name": "Nikos Sculpture Homme EdT 100ml", "merchantName": "10-4", "offerUrl": "https://pricerunner.com/gotostore/v1/partner/DK/6dde64f3b2ac4a0b1752a85b379219fe/adrunner_dk_mandeportalen?productId=3271581", "price": "175.00", "shippingCost": "89.00", "stockStatus": "P\u00e5 lager", "raekkefoelge": 2}, {"id": 3200024124, "categoryName": "projektorer", "imageUrl": "https://www.pricerunner.dk/product/640x640/3009060198/Samsung-LSP7T.jpg", "name": "Samsung LSP7T", "merchantName": "Skiftselv.dk", "offerUrl": "https://pricerunner.com/gotostore/v1/partner/DK/6ce50cdb1a76da742498387f902c5d25/adrunner_dk_mandeportalen?productId=3200024124", "price": "17605.50", "shippingCost": "0.00", "stockStatus": "P\u00e5 lager", "raekkefoelge": 8}, {"id": 3208342676, "categoryName": "tr\u00e5dl\u00f8se h\u00f8retelefoner", "imageUrl": "https://www.pricerunner.dk/product/640x640/3013127966/Apple-AirPods-Pro-2nd-generation-with-MagSafe-Charging-Case-%28USB%E2%80%91C%29.jpg", "name": "Apple AirPods Pro 2nd generation with MagSafe Charging Case (USB\u2011C)", "merchantName": "Amazon DE", "offerUrl": "https://pricerunner.com/gotostore/v1/partner/DK/2ab5c562b8ebfb202cf28f7ec1c803e1/adrunner_dk_mandeportalen?productId=3208342676", "price": "1782.43", "shippingCost": "55.93", "stockStatus": "P\u00e5 lager", "raekkefoelge": 1}, {"id": 3206882156, "categoryName": "tr\u00e5dl\u00f8se h\u00f8retelefoner", "imageUrl": "https://www.pricerunner.dk/product/640x640/3018001251/Sony-WH-1000XM4.jpg", "name": "Sony WH-1000XM4", "merchantName": "NordicElectronics", "offerUrl": "https://pricerunner.com/gotostore/v1/partner/DK/728ac8bc1d12108de808b0035bd42edb/adrunner_dk_mandeportalen?productId=3206882156", "price": "1800.00", "shippingCost": "49.00", "stockStatus": "P\u00e5 lager", "raekkefoelge": 5}, {"id": 3209926564, "categoryName": "jakker herre", "imageUrl": "https://www.pricerunner.dk/product/640x640/3025292372/Arc-teryx-Atom-Hoody-Men-s-Black-Sapphire.jpg", "name": "Arc'teryx Atom Hoody Men's - Black Sapphire", "merchantName": "Eventyrsport", "offerUrl": "https://pricerunner.com/gotostore/v1/partner/DK/a1b26321d1c76f3326ad509a345ea9ad/adrunner_dk_mandeportalen?productId=3209926564", "price": "1878.00", "shippingCost": "0.00", "stockStatus": "P\u00e5 lager", "raekkefoelge": 2}, {"id": 5048089, "categoryName": "smartwatch", "imageUrl": "https://www.pricerunner.dk/product/640x640/1907527121/Garmin-Vivoactive-4s.jpg", "name": "Garmin Vivoactive 4s", "merchantName": "happii.dk", "offerUrl": "https://pricerunner.com/gotostore/v1/partner/DK/ffedf8638457d7823a9c04c637eced9a/adrunner_dk_mandeportalen?productId=5048089", "price": "1882.00", "shippingCost": "33.00", "stockStatus": "P\u00e5 lager", "raekkefoelge": 6}, {"id": 3201783137, "categoryName": "jakker herre", "imageUrl": "https://www.pricerunner.dk/product/640x640/3013250372/Hagloefs-Astral-GTX-Jacket-Tarn-Blue.jpg", "name": "Hagl\u00f6fs Astral GTX Jacket - Tarn Blue", "merchantName": "Friliv.dk", "offerUrl": "https://pricerunner.com/gotostore/v1/partner/DK/c15f92d4063a37ffbbcaf32d3b2bd014/adrunner_dk_mandeportalen?productId=3201783137", "price": "1894.00", "shippingCost": "0.00", "stockStatus": "P\u00e5 lager", "raekkefoelge": 7}, {"id": 3204924270, "categoryName": "varmebl\u00e6sere", "imageUrl": "https://www.pricerunner.dk/product/640x640/3009014797/Frico-Styring-Pcr1-F-pcw.jpg", "name": "Frico Styring Pcr1 F/pcw", "merchantName": "VVSfix.dk", "offerUrl": "https://pricerunner.com/gotostore/v1/partner/DK/28ac691226f8b58c12860a92c72080de/adrunner_dk_mandeportalen?productId=3204924270", "price": "1930.50", "shippingCost": "69.00", "stockStatus": "P\u00e5 lager", "raekkefoelge": 6}, {"id": 3208410174, "categoryName": "smartwatch", "imageUrl": "https://www.pricerunner.dk/product/640x640/3013351872/Garmin-Vivoactive-5.jpg", "name": "Garmin Vivoactive 5", "merchantName": "Amazon DE", "offerUrl": "https://pricerunner.com/gotostore/v1/partner/DK/35218ccbdc4a6d0294ab980b7b001a20/adrunner_dk_mandeportalen?productId=3208410174", "price": "1931.59", "shippingCost": "55.93", "stockStatus": "P\u00e5 lager", "raekkefoelge": 1}, {"id": 3207767670, "categoryName": "tr\u00e5dl\u00f8se h\u00f8retelefoner", "imageUrl": "https://www.pricerunner.dk/product/640x640/3012343909/Sony-WF-1000XM5.jpg", "name": "Sony WF-1000XM5", "merchantName": "NordicElectronics", "offerUrl": "https://pricerunner.com/gotostore/v1/partner/DK/51876f948d9fc0ff161e2d5bcb00efd0/adrunner_dk_mandeportalen?productId=3207767670", "price": "1944.00", "shippingCost": "49.00", "stockStatus": "P\u00e5 lager", "raekkefoelge": 8}, {"id": 5280551, "categoryName": "smartwatch", "imageUrl": "https://www.pricerunner.dk/product/640x640/3000590135/Apple-Watch-SE-40mm-Aluminium-Case-with-Sport-Band.jpg", "name": "Apple Watch SE 40mm Aluminium Case with Sport Band", "merchantName": "GoBlue.dk", "offerUrl": "https://pricerunner.com/gotostore/v1/partner/DK/500344657356bcef8c63b3bb2620dbdd/adrunner_dk_mandeportalen?productId=5280551", "price": "1949.00", "shippingCost": "49.00", "stockStatus": "P\u00e5 lager", "raekkefoelge": 4}, {"id": 3509345, "categoryName": "elektronisk p-skive", "imageUrl": "https://www.pricerunner.dk/product/640x640/1611098728/NeedIT-ParkOne-2.jpg", "name": "NeedIT ParkOne 2", "merchantName": "Pricestar", "offerUrl": "https://pricerunner.com/gotostore/v1/partner/DK/d16ef13ec9aae2cee7d004bbeec31030/adrunner_dk_mandeportalen?productId=3509345", "price": "199.95", "shippingCost": "39.00", "stockStatus": "P\u00e5 lager", "raekkefoelge": 2}, {"id": 4982440, "categoryName": "pladespiller", "imageUrl": "https://www.pricerunner.dk/product/640x640/1889923185/Audio-Technica-AT-LP120XUSB.jpg", "name": "Audio-Technica AT-LP120XUSB", "merchantName": "happii.dk", "offerUrl": "https://pricerunner.com/gotostore/v1/partner/DK/66b07a1b98a083672866a59dc3d7bb6c/adrunner_dk_mandeportalen?productId=4982440", "price": "2089.00", "shippingCost": "33.00", "stockStatus": "P\u00e5 lager", "raekkefoelge": 3}, {"id": 3208721924, "categoryName": "jakker herre", "imageUrl": "https://www.pricerunner.dk/product/640x640/3014935299/Rains-Alta-Long-Puffer-Jacket-Black.jpg", "name": "Rains Alta Long Puffer Jacket - Black", "merchantName": "Magasin Onlineshop", "offerUrl": "https://pricerunner.com/gotostore/v1/partner/DK/f98166137e6d1a676464c4dbfeb67247/adrunner_dk_mandeportalen?productId=3208721924", "price": "2099.30", "shippingCost": "0.00", "stockStatus": "P\u00e5 lager", "raekkefoelge": 1}, {"id": 4758839, "categoryName": "jakker herre", "imageUrl": "https://www.pricerunner.dk/product/640x640/1867327728/Fjaellraeven-Skogsoe-Padded-Jacket-Dark-Navy.jpg", "name": "Fj\u00e4llr\u00e4ven Skogs\u00f6 Padded Jacket - Dark Navy", "merchantName": "Eventyrsport", "offerUrl": "https://pricerunner.com/gotostore/v1/partner/DK/64652aa47a9faf0925535e8ed4030955/adrunner_dk_mandeportalen?productId=4758839", "price": "2171.00", "shippingCost": "0.00", "stockStatus": "P\u00e5 lager", "raekkefoelge": 5}, {"id": 3202492271, "categoryName": "smartwatch", "imageUrl": "https://www.pricerunner.dk/product/640x640/3006295089/Apple-Watch-SE-2022-40mm-Aluminum-Case-with-Sport-Band.jpg", "name": "Apple Watch SE 2022 40mm Aluminum Case with Sport Band", "merchantName": "Komplett.dk", "offerUrl": "https://pricerunner.com/gotostore/v1/partner/DK/1409b7ebdaace7382e9ed93db757c712/adrunner_dk_mandeportalen?productId=3202492271", "price": "2199.00", "shippingCost": "0.00", "stockStatus": "P\u00e5 lager", "raekkefoelge": 3}, {"id": 3207764158, "categoryName": "jakker herre", "imageUrl": "https://www.pricerunner.dk/product/640x640/3025280588/Arc-teryx-Atom-Hoody-Men-s-Black.jpg", "name": "Arc'teryx Atom Hoody Men's - Black", "merchantName": "Eventyrsport", "offerUrl": "https://pricerunner.com/gotostore/v1/partner/DK/3e0d904d65b2e21ad245ab12dc8c46a1/adrunner_dk_mandeportalen?productId=3207764158", "price": "2199.00", "shippingCost": "0.00", "stockStatus": "P\u00e5 lager", "raekkefoelge": 9}, {"id": 3201556081, "categoryName": "tr\u00e5dl\u00f8se h\u00f8retelefoner", "imageUrl": "https://www.pricerunner.dk/product/640x640/3004819494/SteelSeries-Arctis-Nova-Pro-Wireless.jpg", "name": "SteelSeries Arctis Nova Pro Wireless", "merchantName": "Komplett.dk", "offerUrl": "https://pricerunner.com/gotostore/v1/partner/DK/f4cf44d0d0bba4e536bf829eef9f4cdf/adrunner_dk_mandeportalen?productId=3201556081", "price": "2299.00", "shippingCost": "0.00", "stockStatus": "P\u00e5 lager", "raekkefoelge": 9}, {"id": 3207768007, "categoryName": "smartwatch", "imageUrl": "https://www.pricerunner.dk/product/640x640/3012361134/Samsung-Galaxy-Watch6-Classic-47mm-BT.jpg", "name": "Samsung Galaxy Watch6 Classic 47mm BT", "merchantName": "GoBlue.dk", "offerUrl": "https://pricerunner.com/gotostore/v1/partner/DK/33ded94dd8c7bcb6c4627cd048a5890f/adrunner_dk_mandeportalen?productId=3207768007", "price": "2300.00", "shippingCost": "49.00", "stockStatus": "P\u00e5 lager", "raekkefoelge": 7}, {"id": 3205108670, "categoryName": "droner", "imageUrl": "https://www.pricerunner.dk/product/640x640/3009273652/DJI-Mini-2-SE.jpg", "name": "DJI Mini 2 SE", "merchantName": "Droner.dk", "offerUrl": "https://pricerunner.com/gotostore/v1/partner/DK/90188ce8dd49a4c13c6f7cece25522d8/adrunner_dk_mandeportalen?productId=3205108670", "price": "2330.00", "shippingCost": "0.00", "stockStatus": "P\u00e5 lager", "raekkefoelge": 4}, {"id": 3539181, "categoryName": "elektronisk p-skive", "imageUrl": "https://www.pricerunner.dk/product/640x640/1613018552/Samatech-Park-Solar-FS20.jpg", "name": "Samatech Park Solar FS20", "merchantName": "Carvision", "offerUrl": "https://pricerunner.com/gotostore/v1/partner/DK/8b1cdd08f93b9f65f095fed459975ebd/adrunner_dk_mandeportalen?productId=3539181", "price": "236.00", "shippingCost": "45.00", "stockStatus": "P\u00e5 lager", "raekkefoelge": 1}, {"id": 5077554, "categoryName": "elektronisk p-skive", "imageUrl": "https://www.pricerunner.dk/product/640x640/1914565433/Park-Solar-Digital-FS42.jpg", "name": "Park Solar Digital FS42", "merchantName": "jem & fix", "offerUrl": "https://pricerunner.com/gotostore/v1/partner/DK/a631e177cb61fb9e932f2957f3a35131/adrunner_dk_mandeportalen?productId=5077554", "price": "238.00", "shippingCost": "38.00", "stockStatus": "P\u00e5 lager", "raekkefoelge": 3}, {"id": 4457036, "categoryName": "barbermaskiner", "imageUrl": "https://www.pricerunner.dk/product/640x640/1760422596/Philips-OneBlade-QP2520.jpg", "name": "Philips OneBlade QP2520", "merchantName": "Batteribyen.dk", "offerUrl": "https://pricerunner.com/gotostore/v1/partner/DK/9be2f0a62e2a38dce45a116c8568a097/adrunner_dk_mandeportalen?productId=4457036", "price": "239.00", "shippingCost": "29.00", "stockStatus": "P\u00e5 lager", "raekkefoelge": 1}, {"id": 5314818, "categoryName": "skruemaskiner", "imageUrl": "https://www.pricerunner.dk/product/640x640/3015001837/Makita-DHP484RT3J-%283x5.0Ah%29.jpg", "name": "Makita DHP484RT3J (3x5.0Ah)", "merchantName": "Brejnholt Outlet", "offerUrl": "https://pricerunner.com/gotostore/v1/partner/DK/1e362f8cf9b339ff1a26f403ee416303/adrunner_dk_mandeportalen?productId=5314818", "price": "2449.00", "shippingCost": "59.00", "stockStatus": "P\u00e5 lager", "raekkefoelge": 3}, {"id": 3206992880, "categoryName": "tr\u00e5dl\u00f8se h\u00f8retelefoner", "imageUrl": "https://www.pricerunner.dk/product/640x640/3012683346/Sony-WH-1000XM5.jpg", "name": "Sony WH-1000XM5", "merchantName": "NordicElectronics", "offerUrl": "https://pricerunner.com/gotostore/v1/partner/DK/b1d3e6095523c86528f23769965ea3f4/adrunner_dk_mandeportalen?productId=3206992880", "price": "2458.00", "shippingCost": "49.00", "stockStatus": "P\u00e5 lager", "raekkefoelge": 6}, {"id": 4715849, "categoryName": "jakker herre", "imageUrl": "https://www.pricerunner.dk/product/640x640/1869030812/Fjaellraeven-Skogsoe-Padded-Jacket-Black.jpg", "name": "Fj\u00e4llr\u00e4ven Skogs\u00f6 Padded Jacket - Black", "merchantName": "Pro-Outdoor", "offerUrl": "https://pricerunner.com/gotostore/v1/partner/DK/36ce44f46cf5e6620603a3491c29a3c1/adrunner_dk_mandeportalen?productId=4715849", "price": "2474.95", "shippingCost": "0.00", "stockStatus": "P\u00e5 lager", "raekkefoelge": 6}, {"id": 3200320708, "categoryName": "vr headsets", "imageUrl": "https://www.pricerunner.dk/product/640x640/3002610964/Meta-%28Oculus%29-Quest-2-128GB.jpg", "name": "Meta (Oculus) Quest 2 - 128GB", "merchantName": "Elgiganten", "offerUrl": "https://pricerunner.com/gotostore/v1/partner/DK/f1c7c02435a2b1aaca83f9533b65c392/adrunner_dk_mandeportalen?productId=3200320708", "price": "2499.00", "shippingCost": "39.00", "stockStatus": "P\u00e5 lager", "raekkefoelge": 1}, {"id": 3200880477, "categoryName": "smartwatch", "imageUrl": "https://www.pricerunner.dk/product/640x640/3003685055/Garmin-Venu-2-Plus.jpg", "name": "Garmin Venu 2 Plus", "merchantName": "happii.dk", "offerUrl": "https://pricerunner.com/gotostore/v1/partner/DK/b5150252f38b71c23cdc1e8d7441d144/adrunner_dk_mandeportalen?productId=3200880477", "price": "2564.00", "shippingCost": "33.00", "stockStatus": "P\u00e5 lager", "raekkefoelge": 5}, {"id": 3202787121, "categoryName": "varmebl\u00e6sere", "imageUrl": "https://www.pricerunner.dk/product/640x640/3009203055/Gripo-GRI-36555.jpg", "name": "Gripo GRI-36555", "merchantName": "Homeshop.dk", "offerUrl": "https://pricerunner.com/gotostore/v1/partner/DK/115291b402392b4a35efa85faa356b71/adrunner_dk_mandeportalen?productId=3202787121", "price": "260.00", "shippingCost": "49.00", "stockStatus": "P\u00e5 lager", "raekkefoelge": 1}, {"id": 3201392056, "categoryName": "parfumer herre", "imageUrl": "https://www.pricerunner.dk/product/640x640/3004633142/Afnan-9-PM-EdP-100ml.jpg", "name": "Afnan 9 PM EdP 100ml", "merchantName": "Bazta", "offerUrl": "https://pricerunner.com/gotostore/v1/partner/DK/34efe7ad3543c76e728f4589f4303317/adrunner_dk_mandeportalen?productId=3201392056", "price": "279.00", "shippingCost": "39.00", "stockStatus": "P\u00e5 lager", "raekkefoelge": 1}, {"id": 3661596, "categoryName": "elektronisk p-skive", "imageUrl": "https://www.pricerunner.dk/product/640x640/3007723112/NeedIT-Park-Life.jpg", "name": "NeedIT Park Life", "merchantName": "KN-Auto.dk", "offerUrl": "https://pricerunner.com/gotostore/v1/partner/DK/8beda97b6894f75af824b14306e4ed06/adrunner_dk_mandeportalen?productId=3661596", "price": "279.00", "shippingCost": "45.00", "stockStatus": "P\u00e5 lager", "raekkefoelge": 4}, {"id": 3204290823, "categoryName": "droner", "imageUrl": "https://www.pricerunner.dk/product/640x640/3030409013/DJI-Mini-3-Drone.jpg", "name": "DJI Mini 3 Drone", "merchantName": "Fotokoch", "offerUrl": "https://pricerunner.com/gotostore/v1/partner/DK/7db54a97059416ee97aea6784346f5ec/adrunner_dk_mandeportalen?productId=3204290823", "price": "2890.75", "shippingCost": "74.58", "stockStatus": "P\u00e5 lager", "raekkefoelge": 7}, {"id": 3203005732, "categoryName": "vr headsets", "imageUrl": "https://www.pricerunner.dk/product/640x640/3006953694/Pico-4-%28128-GB%29.jpg", "name": "Pico 4 (128 GB)", "merchantName": "Elgiganten", "offerUrl": "https://pricerunner.com/gotostore/v1/partner/DK/e4d671212ad58e542e2b57149de1a02f/adrunner_dk_mandeportalen?productId=3203005732", "price": "2899.00", "shippingCost": "39.00", "stockStatus": "P\u00e5 lager", "raekkefoelge": 7}, {"id": 3200033191, "categoryName": "elektronisk p-skive", "imageUrl": "https://www.pricerunner.dk/product/640x640/3000831968/Samatech-Park-Solar-FS38.jpg", "name": "Samatech Park Solar - FS38", "merchantName": "Nardocar.dk", "offerUrl": "https://pricerunner.com/gotostore/v1/partner/DK/edd88810abdf7065ebda0aa336da7c23/adrunner_dk_mandeportalen?productId=3200033191", "price": "298.00", "shippingCost": "45.00", "stockStatus": "P\u00e5 lager", "raekkefoelge": 8}, {"id": 3057656, "categoryName": "pladespiller", "imageUrl": "https://www.pricerunner.dk/product/640x640/1554122259/Pro-Ject-RPM-1-Carbon.jpg", "name": "Pro-Ject RPM 1 Carbon", "merchantName": "BRL", "offerUrl": "https://pricerunner.com/gotostore/v1/partner/DK/1b735c7e681b182f6a5416cf23b6523b/adrunner_dk_mandeportalen?productId=3057656", "price": "2993.00", "shippingCost": "53.00", "stockStatus": "P\u00e5 lager", "raekkefoelge": 5}, {"id": 3200202386, "categoryName": "elektronisk p-skive", "imageUrl": "https://www.pricerunner.dk/product/640x640/3002168829/NeedIT-ParkOne-Solar.jpg", "name": "NeedIT ParkOne Solar", "merchantName": "KN-Auto.dk", "offerUrl": "https://pricerunner.com/gotostore/v1/partner/DK/0dc4515109bedc979f6516841ab5f02f/adrunner_dk_mandeportalen?productId=3200202386", "price": "306.00", "shippingCost": "45.00", "stockStatus": "P\u00e5 lager", "raekkefoelge": 5}, {"id": 4000152, "categoryName": "skruemaskiner", "imageUrl": "https://www.pricerunner.dk/product/640x640/3007442321/Makita-DDF484RTJ-%282x5.0Ah%29.jpg", "name": "Makita DDF484RTJ (2x5.0Ah)", "merchantName": "Duab", "offerUrl": "https://pricerunner.com/gotostore/v1/partner/DK/af2e34de14314f8680325189a4f31ca6/adrunner_dk_mandeportalen?productId=4000152", "price": "3147.00", "shippingCost": "0.00", "stockStatus": "P\u00e5 lager", "raekkefoelge": 4}, {"id": 5283245, "categoryName": "vr headsets", "imageUrl": "https://www.pricerunner.dk/product/640x640/3000594190/Meta-%28Oculus%29-Quest-2-256GB.jpg", "name": "Meta (Oculus) Quest 2 - 256GB", "merchantName": "Av-Cables", "offerUrl": "https://pricerunner.com/gotostore/v1/partner/DK/144d42ba4889048fdd106012a4c8a8e5/adrunner_dk_mandeportalen?productId=5283245", "price": "3199.00", "shippingCost": "35.00", "stockStatus": "P\u00e5 lager", "raekkefoelge": 6}, {"id": 5086420, "categoryName": "projektorer", "imageUrl": "https://www.pricerunner.dk/product/640x640/1915707082/YG-300-Projektor.jpg", "name": "YG-300 Projektor", "merchantName": "MyTrendyPhone", "offerUrl": "https://pricerunner.com/gotostore/v1/partner/DK/eeb350eb0fb773e8be5fd9a8f5ae817d/adrunner_dk_mandeportalen?productId=5086420", "price": "329.00", "shippingCost": "39.00", "stockStatus": "P\u00e5 lager", "raekkefoelge": 4}, {"id": 3920016, "categoryName": "elektronisk p-skive", "imageUrl": "https://www.pricerunner.dk/product/640x640/1671955446/Park-N-Go-Eco.jpg", "name": "Park N Go Eco", "merchantName": "D\u00e6kbutikken", "offerUrl": "https://pricerunner.com/gotostore/v1/partner/DK/04a991e5c06f1c836901b0062fde537a/adrunner_dk_mandeportalen?productId=3920016", "price": "329.00", "shippingCost": "69.00", "stockStatus": "P\u00e5 lager", "raekkefoelge": 6}, {"id": 5174522, "categoryName": "pladespiller", "imageUrl": "https://www.pricerunner.dk/product/640x640/3000274408/Pro-Ject-T1-Phono-SB.jpg", "name": "Pro-Ject T1 Phono SB", "merchantName": "BRL", "offerUrl": "https://pricerunner.com/gotostore/v1/partner/DK/d0a53d77a0ced9ec571f0a9cd28f16e0/adrunner_dk_mandeportalen?productId=5174522", "price": "3327.00", "shippingCost": "133.00", "stockStatus": "P\u00e5 lager", "raekkefoelge": 8}, {"id": 3539312, "categoryName": "elektronisk p-skive", "imageUrl": "https://www.pricerunner.dk/product/640x640/1576545399/NeedIT-ParkOne-Exclusive.jpg", "name": "NeedIT ParkOne Exclusive", "merchantName": "Nardocar.dk", "offerUrl": "https://pricerunner.com/gotostore/v1/partner/DK/b4336d19d6841c722b63c31a54138f05/adrunner_dk_mandeportalen?productId=3539312", "price": "349.00", "shippingCost": "39.00", "stockStatus": "P\u00e5 lager", "raekkefoelge": 7}, {"id": 5319999, "categoryName": "droner", "imageUrl": "https://www.pricerunner.dk/product/640x640/3000719728/DJI-Mini-2.jpg", "name": "DJI Mini 2", "merchantName": "F\u00f8tex", "offerUrl": "https://pricerunner.com/gotostore/v1/partner/DK/7c4e498058849a49ba092a2780b7c7d5/adrunner_dk_mandeportalen?productId=5319999", "price": "3499.00", "shippingCost": "39.00", "stockStatus": "P\u00e5 lager", "raekkefoelge": 6}, {"id": 4860181, "categoryName": "parfumer herre", "imageUrl": "https://www.pricerunner.dk/product/640x640/1871456710/Rasasi-Hawas-for-Him-EdP-100ml.jpg", "name": "Rasasi Hawas for Him EdP 100ml", "merchantName": "Deloox", "offerUrl": "https://pricerunner.com/gotostore/v1/partner/DK/6a04f40ee00a700fb77b192d50af22c8/adrunner_dk_mandeportalen?productId=4860181", "price": "377.00", "shippingCost": "39.00", "stockStatus": "P\u00e5 lager", "raekkefoelge": 3}, {"id": 3200023938, "categoryName": "tr\u00e5dl\u00f8se h\u00f8retelefoner", "imageUrl": "https://www.pricerunner.dk/product/640x640/3008561639/Apple-AirPods-Max.jpg", "name": "Apple AirPods Max", "merchantName": "Amazon DE", "offerUrl": "https://pricerunner.com/gotostore/v1/partner/DK/71f8e8c02f4ffe26be5915e0805328db/adrunner_dk_mandeportalen?productId=3200023938", "price": "3930.30", "shippingCost": "55.93", "stockStatus": "P\u00e5 lager", "raekkefoelge": 3}, {"id": 5273520, "categoryName": "varmebl\u00e6sere", "imageUrl": "https://www.pricerunner.dk/product/640x640/3000568078/Eveco-CRCMV13.jpg", "name": "Eveco CRCMV13", "merchantName": "Staypro", "offerUrl": "https://pricerunner.com/gotostore/v1/partner/DK/35caec0e71823a10ab3a071b5717fd70/adrunner_dk_mandeportalen?productId=5273520", "price": "3933.00", "shippingCost": "249.00", "stockStatus": "P\u00e5 lager", "raekkefoelge": 8}, {"id": 3095487, "categoryName": "parfumer herre", "imageUrl": "https://www.pricerunner.dk/product/640x640/3016305587/Giorgio-Armani-Acqua-Di-Gio-Pour-Homme-EdT-100ml.jpg", "name": "Giorgio Armani Acqua Di Gio Pour Homme EdT 100ml", "merchantName": "Salling", "offerUrl": "https://pricerunner.com/gotostore/v1/partner/DK/d8cf095e821b8ef0a0aa2d0c1163d8d0/adrunner_dk_mandeportalen?productId=3095487", "price": "437.50", "shippingCost": "0.00", "stockStatus": "P\u00e5 lager", "raekkefoelge": 7}, {"id": 3203005936, "categoryName": "vr headsets", "imageUrl": "https://www.pricerunner.dk/product/640x640/3006955036/Sony-Playstation-VR2.jpg", "name": "Sony Playstation VR2", "merchantName": "NordicElectronics", "offerUrl": "https://pricerunner.com/gotostore/v1/partner/DK/694dbe451861a4dd64f87b097ef15a0e/adrunner_dk_mandeportalen?productId=3203005936", "price": "4388.00", "shippingCost": "49.00", "stockStatus": "P\u00e5 lager", "raekkefoelge": 3}, {"id": 3208711717, "categoryName": "vr headsets", "imageUrl": "https://www.pricerunner.dk/product/640x640/3013617636/Meta-%28Oculus%29-Quest-3-Virtual-Reality-Headset-128GB.jpg", "name": "Meta (Oculus) Quest 3 Virtual Reality Headset 128GB", "merchantName": "Komplett.dk", "offerUrl": "https://pricerunner.com/gotostore/v1/partner/DK/2c8b40c134788b4b07bbfc31e2e93c7d/adrunner_dk_mandeportalen?productId=3208711717", "price": "4399.00", "shippingCost": "0.00", "stockStatus": "P\u00e5 lager", "raekkefoelge": 2}, {"id": 3202621042, "categoryName": "barbermaskiner", "imageUrl": "https://www.pricerunner.dk/product/640x640/3006502018/Philips-OneBlade-Pro-QP6541.jpg", "name": "Philips OneBlade Pro QP6541", "merchantName": "happii.dk", "offerUrl": "https://pricerunner.com/gotostore/v1/partner/DK/2202979fdda356822bea227cc3b2a456/adrunner_dk_mandeportalen?productId=3202621042", "price": "446.00", "shippingCost": "33.00", "stockStatus": "P\u00e5 lager", "raekkefoelge": 2}, {"id": 3202747115, "categoryName": "projektorer", "imageUrl": "https://www.pricerunner.dk/product/640x640/3006885985/Epson-CO-FH02.jpg", "name": "Epson CO-FH02", "merchantName": "happii.dk", "offerUrl": "https://pricerunner.com/gotostore/v1/partner/DK/e956ca3ad92576ff1617751ed3ab9e0a/adrunner_dk_mandeportalen?productId=3202747115", "price": "4514.00", "shippingCost": "33.00", "stockStatus": "P\u00e5 lager", "raekkefoelge": 6}, {"id": 4734893, "categoryName": "parfumer herre", "imageUrl": "https://www.pricerunner.dk/product/640x640/3016580433/Yves-Saint-Laurent-Y-Men-EdP-60ml.jpg", "name": "Yves Saint Laurent Y Men EdP 60ml", "merchantName": "Parfumdreams.dk", "offerUrl": "https://pricerunner.com/gotostore/v1/partner/DK/4bb45927d994cdd0ed03d5d12f912b7c/adrunner_dk_mandeportalen?productId=4734893", "price": "465.00", "shippingCost": "29.00", "stockStatus": "P\u00e5 lager", "raekkefoelge": 6}, {"id": 3200347231, "categoryName": "parfumer herre", "imageUrl": "https://www.pricerunner.dk/product/640x640/3002727409/Azzaro-Most-Wanted-EdP-100ml.jpg", "name": "Azzaro Most Wanted EdP 100ml", "merchantName": "Parfumdreams.dk", "offerUrl": "https://pricerunner.com/gotostore/v1/partner/DK/0f737312751ce4a601907d832b0aab50/adrunner_dk_mandeportalen?productId=3200347231", "price": "484.00", "shippingCost": "29.00", "stockStatus": "P\u00e5 lager", "raekkefoelge": 8}, {"id": 3201382001, "categoryName": "droner", "imageUrl": "https://www.pricerunner.dk/product/640x640/3004667283/DJI-Mini-3-Pro-N1-Controller.jpg", "name": "DJI Mini 3 Pro + N1 Controller", "merchantName": "Fotokoch", "offerUrl": "https://pricerunner.com/gotostore/v1/partner/DK/941dd36edeb132d18182b7195c9d1c92/adrunner_dk_mandeportalen?productId=3201382001", "price": "5162.57", "shippingCost": "74.58", "stockStatus": "P\u00e5 lager", "raekkefoelge": 8}, {"id": 3203269811, "categoryName": "vr headsets", "imageUrl": "https://www.pricerunner.dk/product/640x640/3007249316/Sony-Playstation-VR2-Horizon-Call-Of-The-Mountain-Bundle.jpg", "name": "Sony Playstation VR2 - Horizon: Call Of The Mountain Bundle", "merchantName": "Komplett.dk", "offerUrl": "https://pricerunner.com/gotostore/v1/partner/DK/d5a43961d213452a2b29f162ec6c3554/adrunner_dk_mandeportalen?productId=3203269811", "price": "5189.00", "shippingCost": "0.00", "stockStatus": "P\u00e5 lager", "raekkefoelge": 5}, {"id": 5171347, "categoryName": "barbermaskiner", "imageUrl": "https://www.pricerunner.dk/product/640x640/3006625552/Babyliss-Japanese-Steel-E990E.jpg", "name": "Babyliss Japanese Steel E990E", "merchantName": "NordicFeel", "offerUrl": "https://pricerunner.com/gotostore/v1/partner/DK/298eed9e1ae075a06c690e23a1c698b2/adrunner_dk_mandeportalen?productId=5171347", "price": "522.00", "shippingCost": "39.00", "stockStatus": "P\u00e5 lager", "raekkefoelge": 7}, {"id": 5061002, "categoryName": "parfumer herre", "imageUrl": "https://www.pricerunner.dk/product/640x640/1910581627/Valentino-Born-in-Roma-Uomo-EdT-100ml.jpg", "name": "Valentino Born in Roma Uomo EdT 100ml", "merchantName": "Parfumdreams.dk", "offerUrl": "https://pricerunner.com/gotostore/v1/partner/DK/74e911ad82c98d75bf419159467d04b6/adrunner_dk_mandeportalen?productId=5061002", "price": "554.00", "shippingCost": "0.00", "stockStatus": "P\u00e5 lager", "raekkefoelge": 9}, {"id": 3205014053, "categoryName": "parfumer herre", "imageUrl": "https://www.pricerunner.dk/product/640x640/3009154598/Valentino-Born-in-Roma-Uomo-Intense-EdP-50ml.jpg", "name": "Valentino Born in Roma Uomo Intense EdP 50ml", "merchantName": "Sephora", "offerUrl": "https://pricerunner.com/gotostore/v1/partner/DK/f4b25df71e95223fd3074597d619c7ee/adrunner_dk_mandeportalen?productId=3205014053", "price": "559.00", "shippingCost": "0.00", "stockStatus": "P\u00e5 lager", "raekkefoelge": 5}, {"id": 3208510394, "categoryName": "vr headsets", "imageUrl": "https://www.pricerunner.dk/product/640x640/3013294993/Meta-%28Oculus%29-Quest-3-512GB.jpg", "name": "Meta (Oculus) Quest 3 - 512GB", "merchantName": "Komplett.dk", "offerUrl": "https://pricerunner.com/gotostore/v1/partner/DK/b0290ce2c0f4fb937ba78bf74d04d70b/adrunner_dk_mandeportalen?productId=3208510394", "price": "5599.00", "shippingCost": "0.00", "stockStatus": "P\u00e5 lager", "raekkefoelge": 4}, {"id": 5269547, "categoryName": "varmebl\u00e6sere", "imageUrl": "https://www.pricerunner.dk/product/640x640/3000557449/Frico-PCW232S.jpg", "name": "Frico PCW232S", "merchantName": "Staypro", "offerUrl": "https://pricerunner.com/gotostore/v1/partner/DK/bb79d6f5176d89a8cfab7493847007db/adrunner_dk_mandeportalen?productId=5269547", "price": "5601.00", "shippingCost": "299.00", "stockStatus": "P\u00e5 lager", "raekkefoelge": 4}, {"id": 3208174432, "categoryName": "projektorer", "imageUrl": "https://www.pricerunner.dk/product/640x640/3013542408/Samsung-The-Freestyle-2nd-Gen.jpg", "name": "Samsung The Freestyle 2nd Gen", "merchantName": "DataWorld", "offerUrl": "https://pricerunner.com/gotostore/v1/partner/DK/cd6d66e853397cec1d31b71fd517e4f5/adrunner_dk_mandeportalen?productId=3208174432", "price": "5745.00", "shippingCost": "38.00", "stockStatus": "P\u00e5 lager", "raekkefoelge": 1}, {"id": 3047904, "categoryName": "barbermaskiner", "imageUrl": "https://www.pricerunner.dk/product/640x640/3015766580/Philips-Series-9000-HC9450.jpg", "name": "Philips Series 9000 HC9450", "merchantName": "Dealicious", "offerUrl": "https://pricerunner.com/gotostore/v1/partner/DK/89bcf31dc0f8c5e3d73d9cbc1dc50fab/adrunner_dk_mandeportalen?productId=3047904", "price": "595.00", "shippingCost": "0.00", "stockStatus": "P\u00e5 lager", "raekkefoelge": 3}, {"id": 3201388198, "categoryName": "droner", "imageUrl": "https://www.pricerunner.dk/product/640x640/3014935033/DJI-Mini-3-Pro-Smart-Controller.jpg", "name": "DJI Mini 3 Pro + Smart Controller", "merchantName": "SkyPilot.dk", "offerUrl": "https://pricerunner.com/gotostore/v1/partner/DK/e3c3ec914bf357311ff65cfd3e8458f8/adrunner_dk_mandeportalen?productId=3201388198", "price": "6189.00", "shippingCost": "0.00", "stockStatus": "P\u00e5 lager", "raekkefoelge": 3}, {"id": 3202621560, "categoryName": "barbermaskiner", "imageUrl": "https://www.pricerunner.dk/product/640x640/3006502535/Philips-OneBlade-Pro-360-QP6651.jpg", "name": "Philips OneBlade Pro 360 QP6651", "merchantName": "Amazon DE", "offerUrl": "https://pricerunner.com/gotostore/v1/partner/DK/39fe132f61473ad66c6cd25fb8bf1a8e/adrunner_dk_mandeportalen?productId=3202621560", "price": "633.85", "shippingCost": "55.93", "stockStatus": "P\u00e5 lager", "raekkefoelge": 9}, {"id": 3200171075, "categoryName": "vr headsets", "imageUrl": "https://www.pricerunner.dk/product/640x640/3003148799/HTC-Vive-Pro-2-Headset.jpg", "name": "HTC Vive Pro 2 - Headset", "merchantName": "happii.dk", "offerUrl": "https://pricerunner.com/gotostore/v1/partner/DK/d4234950bdc43eb5de37efd259a6b966/adrunner_dk_mandeportalen?productId=3200171075", "price": "6399.00", "shippingCost": "33.00", "stockStatus": "P\u00e5 lager", "raekkefoelge": 9}, {"id": 3202531679, "categoryName": "projektorer", "imageUrl": "https://www.pricerunner.dk/product/640x640/3006379667/Epson-EH-TW6150.jpg", "name": "Epson EH-TW6150", "merchantName": "happii.dk", "offerUrl": "https://pricerunner.com/gotostore/v1/partner/DK/e15b0865026bf60216fefd173b49e55e/adrunner_dk_mandeportalen?productId=3202531679", "price": "6445.00", "shippingCost": "33.00", "stockStatus": "P\u00e5 lager", "raekkefoelge": 7}, {"id": 3148971, "categoryName": "skruemaskiner", "imageUrl": "https://www.pricerunner.dk/product/640x640/3014994591/Makita-DTD152Z-Solo.jpg", "name": "Makita DTD152Z Solo", "merchantName": "Shopexpert", "offerUrl": "https://pricerunner.com/gotostore/v1/partner/DK/ca7564ce94f693b7739ea5a5dcc0926f/adrunner_dk_mandeportalen?productId=3148971", "price": "649.00", "shippingCost": "39.00", "stockStatus": "P\u00e5 lager", "raekkefoelge": 1}, {"id": 5269434, "categoryName": "varmebl\u00e6sere", "imageUrl": "https://www.pricerunner.dk/product/640x640/3000557091/Frico-PCW332S.jpg", "name": "Frico PCW332S", "merchantName": "Staypro", "offerUrl": "https://pricerunner.com/gotostore/v1/partner/DK/038f435bc79157746313e8d6c777b2a6/adrunner_dk_mandeportalen?productId=5269434", "price": "6668.00", "shippingCost": "249.00", "stockStatus": "P\u00e5 lager", "raekkefoelge": 5}, {"id": 3208336696, "categoryName": "smartwatch", "imageUrl": "https://www.pricerunner.dk/product/640x640/3013221792/Apple-Watch-Ultra-2-Titanium-Case-with-Alpine-Loop.jpg", "name": "Apple Watch Ultra 2 Titanium Case with Alpine Loop", "merchantName": "NordicElectronics", "offerUrl": "https://pricerunner.com/gotostore/v1/partner/DK/a4edd674cd3421b7a284c60663f5eb71/adrunner_dk_mandeportalen?productId=3208336696", "price": "6945.00", "shippingCost": "49.00", "stockStatus": "P\u00e5 lager", "raekkefoelge": 2}, {"id": 3200715461, "categoryName": "projektorer", "imageUrl": "https://www.pricerunner.dk/product/640x640/3003407301/Xgimi-HALO.jpg", "name": "Xgimi HALO+", "merchantName": "Muziker", "offerUrl": "https://pricerunner.com/gotostore/v1/partner/DK/b7d9cfd5e731b7b691103dca9059d9a4/adrunner_dk_mandeportalen?productId=3200715461", "price": "6959.00", "shippingCost": "0.00", "stockStatus": "P\u00e5 lager", "raekkefoelge": 3}, {"id": 3143026, "categoryName": "skruemaskiner", "imageUrl": "https://www.pricerunner.dk/product/640x640/3014991502/Dewalt-DCF887N-XJ-Solo.jpg", "name": "Dewalt DCF887N-XJ Solo", "merchantName": "Prishammeren", "offerUrl": "https://pricerunner.com/gotostore/v1/partner/DK/89989fb39795d7f3e8f4aa53397d7535/adrunner_dk_mandeportalen?productId=3143026", "price": "699.00", "shippingCost": "45.00", "stockStatus": "P\u00e5 lager", "raekkefoelge": 7}, {"id": 3206723485, "categoryName": "parfumer herre", "imageUrl": "https://www.pricerunner.dk/product/640x640/3025292376/Jean-Paul-Gaultier-Le-Male-Elixir-EdP-125ml.jpg", "name": "Jean Paul Gaultier Le Male Elixir EdP 125ml", "merchantName": "Sephora", "offerUrl": "https://pricerunner.com/gotostore/v1/partner/DK/cafcd7e94222e0040b35f3e224cd74fb/adrunner_dk_mandeportalen?productId=3206723485", "price": "739.00", "shippingCost": "0.00", "stockStatus": "P\u00e5 lager", "raekkefoelge": 4}, {"id": 3208508824, "categoryName": "droner", "imageUrl": "https://www.pricerunner.dk/product/640x640/3014749080/DJI-Mini-4-Pro-Smart-Controller.jpg", "name": "DJI Mini 4 Pro + Smart Controller", "merchantName": "Fotokoch", "offerUrl": "https://pricerunner.com/gotostore/v1/partner/DK/e5a098376e4d8453f2274355adbb0161/adrunner_dk_mandeportalen?productId=3208508824", "price": "7434.39", "shippingCost": "74.58", "stockStatus": "P\u00e5 lager", "raekkefoelge": 2}, {"id": 4565450, "categoryName": "droner", "imageUrl": "https://www.pricerunner.dk/product/640x640/1829117504/Ryze-Tello.jpg", "name": "Ryze Tello", "merchantName": "happii.dk", "offerUrl": "https://pricerunner.com/gotostore/v1/partner/DK/e61047e575a455fd887aba97c33a69d3/adrunner_dk_mandeportalen?productId=4565450", "price": "787.00", "shippingCost": "33.00", "stockStatus": "P\u00e5 lager", "raekkefoelge": 5}, {"id": 3206407934, "categoryName": "droner", "imageUrl": "https://www.pricerunner.dk/product/640x640/3010642898/DJI-Avata-Pro-View-Combo-Drone.jpg", "name": "DJI Avata Pro View Combo Drone", "merchantName": "Scandinavian Photo", "offerUrl": "https://pricerunner.com/gotostore/v1/partner/DK/682a4cbae0a842917d7853586d91698c/adrunner_dk_mandeportalen?productId=3206407934", "price": "7890.00", "shippingCost": "0.00", "stockStatus": "P\u00e5 lager", "raekkefoelge": 9}, {"id": 4948167, "categoryName": "varmebl\u00e6sere", "imageUrl": "https://www.pricerunner.dk/product/640x640/1909583133/Hydro-X-CX-9030005-WW.jpg", "name": "Hydro X CX-9030005-WW", "merchantName": "happii.dk", "offerUrl": "https://pricerunner.com/gotostore/v1/partner/DK/e860c352d0610c013bb95950f9f7cebd/adrunner_dk_mandeportalen?productId=4948167", "price": "875.00", "shippingCost": "33.00", "stockStatus": "P\u00e5 lager", "raekkefoelge": 3}, {"id": 4687044, "categoryName": "tr\u00e5dl\u00f8se h\u00f8retelefoner", "imageUrl": "https://www.pricerunner.dk/product/640x640/3003053650/Apple-AirPods-%282nd-generation%29-2019.jpg", "name": "Apple AirPods (2nd generation) 2019", "merchantName": "GoBlue.dk", "offerUrl": "https://pricerunner.com/gotostore/v1/partner/DK/94fb799438f3801677f6a7383d89580e/adrunner_dk_mandeportalen?productId=4687044", "price": "883.00", "shippingCost": "49.00", "stockStatus": "P\u00e5 lager", "raekkefoelge": 2}, {"id": 4953882, "categoryName": "pladespiller", "imageUrl": "https://www.pricerunner.dk/product/640x640/1878515518/Technics-SL-1500C.jpg", "name": "Technics SL-1500C", "merchantName": "Milo Lyd & Billede", "offerUrl": "https://pricerunner.com/gotostore/v1/partner/DK/1cd3266b72fce1dcf202005029b695f0/adrunner_dk_mandeportalen?productId=4953882", "price": "8849.00", "shippingCost": "0.00", "stockStatus": "P\u00e5 lager", "raekkefoelge": 6}, {"id": 3208509105, "categoryName": "droner", "imageUrl": "https://www.pricerunner.dk/product/640x640/3013655155/DJI-Mini-4-Pro-Drone-Fly-More-Combo.jpg", "name": "DJI Mini 4 Pro Drone Fly More Combo", "merchantName": "ELEXTRA.dk", "offerUrl": "https://pricerunner.com/gotostore/v1/partner/DK/c6e1f458a5495f48584c35d0de9d4bde/adrunner_dk_mandeportalen?productId=3208509105", "price": "8945.00", "shippingCost": "0.00", "stockStatus": "P\u00e5 lager", "raekkefoelge": 1}, {"id": 3200369391, "categoryName": "vr headsets", "imageUrl": "https://www.pricerunner.dk/product/640x640/3036309017/HTC-VIVE-PRO-2-Full-kit.jpg", "name": "HTC VIVE PRO 2 - Full kit", "merchantName": "Komplett.dk", "offerUrl": "https://pricerunner.com/gotostore/v1/partner/DK/99f2a9085b43d24fcd7c8e137da72490/adrunner_dk_mandeportalen?productId=3200369391", "price": "8999.00", "shippingCost": "0.00", "stockStatus": "P\u00e5 lager", "raekkefoelge": 8}, {"id": 3120531, "categoryName": "barbermaskiner", "imageUrl": "https://www.pricerunner.dk/product/640x640/3025292133/Babyliss-E650E.jpg", "name": "Babyliss E650E", "merchantName": "happii.dk", "offerUrl": "https://pricerunner.com/gotostore/v1/partner/DK/7e2996ce2af4b77dcad2efa12ad5e2d0/adrunner_dk_mandeportalen?productId=3120531", "price": "90.00", "shippingCost": "33.00", "stockStatus": "P\u00e5 lager", "raekkefoelge": 8}, {"id": 5254119, "categoryName": "barbermaskiner", "imageUrl": "https://www.pricerunner.dk/product/640x640/3000517116/Philips-9000-Prestige-BT9810.jpg", "name": "Philips 9000 Prestige BT9810", "merchantName": "Butik24", "offerUrl": "https://pricerunner.com/gotostore/v1/partner/DK/866232e2f4d6a7ad6d8c07a206217c1e/adrunner_dk_mandeportalen?productId=5254119", "price": "939.00", "shippingCost": "0.00", "stockStatus": "P\u00e5 lager", "raekkefoelge": 5}, {"id": 5112118, "categoryName": "jakker herre", "imageUrl": "https://www.pricerunner.dk/product/640x640/3000074924/Patagonia-Men-s-Retro-Pile-Fleece-Jacket-Black.jpg", "name": "Patagonia Men's Retro Pile Fleece Jacket - Black", "merchantName": "Bjergk\u00e6den", "offerUrl": "https://pricerunner.com/gotostore/v1/partner/DK/9940150c3b4d2085b80a095c79f9b22d/adrunner_dk_mandeportalen?productId=5112118", "price": "959.20", "shippingCost": "0.00", "stockStatus": "P\u00e5 lager", "raekkefoelge": 8}, {"id": 3200189968, "categoryName": "smartwatch", "imageUrl": "https://www.pricerunner.dk/product/640x640/3002121946/Garmin-Forerunner-55.jpg", "name": "Garmin Forerunner 55", "merchantName": "F\u00f8tex", "offerUrl": "https://pricerunner.com/gotostore/v1/partner/DK/30d8e4085d5b5ef599f621c8507721ca/adrunner_dk_mandeportalen?productId=3200189968", "price": "999.00", "shippingCost": "39.00", "stockStatus": "P\u00e5 lager", "raekkefoelge": 9}, {"id": 4385130, "categoryName": "skruemaskiner", "imageUrl": "https://www.pricerunner.dk/product/640x640/1746580506/Bosch-GSR-12V-15-Professional-%282x2.0Ah%29.jpg", "name": "Bosch GSR 12V-15 Professional (2x2.0Ah)", "merchantName": "24hshop.dk", "offerUrl": "https://pricerunner.com/gotostore/v1/partner/DK/12ca768eb57d71b2c2d7307a42d4be3e/adrunner_dk_mandeportalen?productId=4385130", "price": "999.00", "shippingCost": "49.00", "stockStatus": "P\u00e5 lager", "raekkefoelge": 5}]